basic_math_operations/__init__.py
basic_math_operations/operations.py
aryan_basic_math_operations-1.0.1.dist-info/METADATA
aryan_basic_math_operations-1.0.1.dist-info/WHEEL
aryan_basic_math_operations-1.0.1.dist-info/top_level.txt
aryan_basic_math_operations-1.0.1.dist-info/RECORD
