Metadata-Version: 2.1
Name: aryan-basic_math_operations
Version: 1.0.1
Summary: A Python package for basic mathematical operations
Home-page: https://github.com/AryanAAB/Summer-School-on-Embedded-Systems-and-Robotics
Author: Aryan
Author-email: aryanbansal310@gmail.com
License: MIT
